{
  "title": "Формы для облицовки и фасадной плитки: цены | FORMASUPER",
  "description": "Формы для фасадной плитки и облицовки: сланец, рустовый камень, кирпич, дикий камень. Каталог FORMASUPER.",
  "h1": "Формы облицовки и фасадной плитки",
  "text": "Раздел «Формы облицовки и фасадной плитки» предназначен для производства декоративных бетонных элементов для стен, фасадов, цоколей и интерьерных акцентных поверхностей. В каталоге представлены облицовочный сланец, рустовый камень, облицовочная плитка, кирпич и дикий камень в нескольких форматах. Это отдельное направление, которое помогает производителю выйти за рамки только тротуарной плитки и предложить покупателям продукцию для вертикальных поверхностей.\n\nФормы из ударопрочного полипропилена подходят для многократного изготовления облицовочных элементов. В таблице указаны артикулы, размеры, количество на м2 и цены за штуку. Раздел может быть интересен производителям декоративного камня, продавцам отделочных материалов, оптовым покупателям и маркетплейс-селлерам. Для расчета комплекта или оптовых условий отправьте заявку через сайт.",
  "faq": [{"question":"Что можно производить в этом разделе?","answer":"Фасадную и облицовочную плитку, декоративный камень и кирпичные элементы."},{"question":"Подходит ли продукция только для улицы?","answer":"Формы используются для изготовления облицовочных элементов; область применения зависит от готового материала и технологии."},{"question":"Есть ли разные фактуры?","answer":"Да, в каталоге есть сланец, рустовый камень, кирпич и дикий камень."}]
}
